{
  "project_info": {
    "project_number": "869502851227",
    "project_id": "englishkidsapp-fe0af",
    "storage_bucket": "englishkidsapp-fe0af.firebasestorage.app"
  },
  "client": [
    {
      "client_info": {
        "mobilesdk_app_id": "1:869502851227:android:0b8e6dc971f0049aec8e3e",
        "android_client_info": {
          "package_name": "com.sabag.englishapp.english_learning_app"
        }
      },
      "oauth_client": [],
      "api_key": [
        {
          "current_key": "AIzaSyAm9glf6JeaaTffQX2uhirqGO4V8ez8Vew"
        }
      ],
      "services": {
        "appinvite_service": {
          "other_platform_oauth_client": []
        }
      }
    }
  ],
  "configuration_version": "1"
}